meggie_fooof/__init__.py
meggie_fooof/configuration.json
meggie_fooof/actions/__init__.py
meggie_fooof/actions/__pycache__/__init__.py
meggie_fooof/actions/fooof_create/__init__.py
meggie_fooof/actions/fooof_create/configuration.json
meggie_fooof/actions/fooof_create/controller/fooof.py
meggie_fooof/actions/fooof_create/dialogs/__init__.py
meggie_fooof/actions/fooof_create/dialogs/createReportDialogMain.py
meggie_fooof/actions/fooof_create/dialogs/createReportDialogUi.py
meggie_fooof/actions/fooof_create/tests/__init__.py
meggie_fooof/actions/fooof_create/tests/test_fooof_create.py
meggie_fooof/actions/fooof_delete/__init__.py
meggie_fooof/actions/fooof_delete/configuration.json
meggie_fooof/actions/fooof_delete/tests/__init__.py
meggie_fooof/actions/fooof_delete/tests/test_fooof_delete.py
meggie_fooof/actions/fooof_delete_from_all/__init__.py
meggie_fooof/actions/fooof_delete_from_all/configuration.json
meggie_fooof/actions/fooof_delete_from_all/tests/__init__.py
meggie_fooof/actions/fooof_delete_from_all/tests/test_fooof_delete_from_all.py
meggie_fooof/actions/fooof_info/__init__.py
meggie_fooof/actions/fooof_info/configuration.json
meggie_fooof/actions/fooof_info/tests/__init__.py
meggie_fooof/actions/fooof_info/tests/test_fooof_info.py
meggie_fooof/actions/fooof_plot/__init__.py
meggie_fooof/actions/fooof_plot/configuration.json
meggie_fooof/actions/fooof_plot/controller/__init__.py
meggie_fooof/actions/fooof_plot/controller/fooof.py
meggie_fooof/actions/fooof_plot/tests/__init__.py
meggie_fooof/actions/fooof_plot/tests/test_fooof_plot_all_channels.py
meggie_fooof/actions/fooof_plot/tests/test_fooof_plot_channel_averages.py
meggie_fooof/actions/fooof_save/__init__.py
meggie_fooof/actions/fooof_save/configuration.json
meggie_fooof/actions/fooof_save/controller/__init__.py
meggie_fooof/actions/fooof_save/controller/fooof.py
meggie_fooof/actions/fooof_save/tests/__init__.py
meggie_fooof/actions/fooof_save/tests/test_fooof_save_all_channels.py
meggie_fooof-0.4.0.dist-info/METADATA
meggie_fooof-0.4.0.dist-info/WHEEL
meggie_fooof-0.4.0.dist-info/top_level.txt
meggie_fooof-0.4.0.dist-info/RECORD
